gemini_mcp/__init__.py
gemini_mcp/cli.py
eyycheev_gemini_mcp-0.1.3.dist-info/METADATA
eyycheev_gemini_mcp-0.1.3.dist-info/WHEEL
eyycheev_gemini_mcp-0.1.3.dist-info/entry_points.txt
eyycheev_gemini_mcp-0.1.3.dist-info/RECORD
