Metadata-Version: 2.4
Name: eyycheev-gemini-mcp
Version: 0.1.3
Summary: uvx wrapper that launches @eyycheev/gemini-mcp (Node) via npx
Requires-Python: >=3.8
